config/__init__.py
vietocr/__init__.py
vietocr/predict.py
vietocr/train.py
vietocr/loader/__init__.py
vietocr/loader/aug.py
vietocr/loader/dataloader.py
vietocr/loader/dataloader_v1.py
vietocr/model/__init__.py
vietocr/model/beam.py
vietocr/model/trainer.py
vietocr/model/transformerocr.py
vietocr/model/vocab.py
vietocr/model/backbone/__init__.py
vietocr/model/backbone/cnn.py
vietocr/model/backbone/resnet.py
vietocr/model/backbone/vgg.py
vietocr/model/seqmodel/__init__.py
vietocr/model/seqmodel/convseq2seq.py
vietocr/model/seqmodel/seq2seq.py
vietocr/model/seqmodel/transformer.py
vietocr/optim/__init__.py
vietocr/optim/labelsmoothingloss.py
vietocr/optim/optim.py
vietocr/tool/__init__.py
vietocr/tool/config.py
vietocr/tool/create_dataset.py
vietocr/tool/logger.py
vietocr/tool/predictor.py
vietocr/tool/translate.py
vietocr/tool/utils.py
vietocr-0.3.13.dist-info/LICENSE
vietocr-0.3.13.dist-info/METADATA
vietocr-0.3.13.dist-info/WHEEL
vietocr-0.3.13.dist-info/top_level.txt
vietocr-0.3.13.dist-info/RECORD
