Metadata-Version: 2.1
Name: vietocr
Version: 0.3.13
Summary: Transformer base text detection
Home-page: https://github.com/pbcquoc/vietocr
Author: pbcquoc
Author-email: pbcquoc@gmail.com
Classifier: Programming Language :: Python :: 3
Classifier: License :: OSI Approved :: MIT License
Classifier: Operating System :: OS Independent
Requires-Python: >=3.6
License-File: LICENSE
Requires-Dist: einops==0.2.0
Requires-Dist: gdown==4.4.0
Requires-Dist: prefetch_generator==1.0.1
Requires-Dist: imgaug==0.4.0
Requires-Dist: albumentations==1.4.2
Requires-Dist: lmdb>=1.0.0
Requires-Dist: scikit-image>=0.21.0
Requires-Dist: pillow==10.2.0
